dashlog/__init__.py
dashlog/dashlog.py
dashlog-0.0.2.dist-info/METADATA
dashlog-0.0.2.dist-info/WHEEL
dashlog-0.0.2.dist-info/licenses/LICENSE
dashlog-0.0.2.dist-info/RECORD
