Metadata-Version: 2.1
Name: dashlog
Version: 0.0.2
Summary: Official wrapper over the dashlog.app api
Project-URL: Website, https://dashlog.app
Project-URL: Github, https://github.com/AdrCor/dashlog-py
Author-email: Adrien Corre <adriencorre.dev@gmail.com>
License-File: LICENSE
Classifier: License :: OSI Approved :: MIT License
Classifier: Operating System :: OS Independent
Classifier: Programming Language :: Python :: 3
Requires-Python: >=3.7
Requires-Dist: requests>2
